Metadata-Version: 2.1
Name: odoo13-addon-graphql-base
Version: 13.0.1.0.1.dev6
Summary: Base GraphQL/GraphiQL controller
Home-page: https://github.com/OCA/rest-framework
Author: ACSONE SA/NV,Odoo Community Association (OCA)
Author-email: support@odoo-community.org
License: LGPL-3
Platform: UNKNOWN
Classifier: Programming Language :: Python
Classifier: Framework :: Odoo
Classifier: Framework :: Odoo :: 13.0
Classifier: License :: OSI Approved :: GNU Lesser General Public License v3 (LGPLv3)
Classifier: Development Status :: 4 - Beta
Requires-Python: >=3.5
Requires-Dist: graphene <3
Requires-Dist: graphql-server-core
Requires-Dist: odoo <13.1dev,>=13.0a
